microbot/MicroBot.py
microbot/__init__.py
microbot/search.py
microbot/words.py
microbotpkg-0.0.3.dist-info/METADATA
microbotpkg-0.0.3.dist-info/WHEEL
microbotpkg-0.0.3.dist-info/top_level.txt
microbotpkg-0.0.3.dist-info/RECORD
