Metadata-Version: 2.1
Name: microbotpkg
Version: 0.0.3
Summary: An Intelligent Bot Framework to build simple yet powerful Assistance Bots.
Home-page: UNKNOWN
Author: Juan Carlos Juárez
Author-email: <jc.juarezgarcia@outlook.com>
License: UNKNOWN
Keywords: python,Bot,Framework
Platform: UNKNOWN
Classifier: Development Status :: 1 - Planning
Classifier: Intended Audience :: Developers
Classifier: Programming Language :: Python :: 3
Classifier: Operating System :: Unix
Classifier: Operating System :: MacOS :: MacOS X
Classifier: Operating System :: Microsoft :: Windows
Requires-Dist: lxml
Requires-Dist: googlesearch-python
Requires-Dist: animation
Requires-Dist: pyttsx3
Requires-Dist: beautifulsoup4
